pharaglow/__init__.py
pharaglow/extract.py
pharaglow/features.py
pharaglow/io.py
pharaglow/run.py
pharaglow/tracking.py
pharaglow/util.py
pharaglow-0.9.6.dist-info/LICENSE
pharaglow-0.9.6.dist-info/METADATA
pharaglow-0.9.6.dist-info/WHEEL
pharaglow-0.9.6.dist-info/top_level.txt
pharaglow-0.9.6.dist-info/zip-safe
pharaglow-0.9.6.dist-info/RECORD
