Metadata-Version: 2.1
Name: pharaglow
Version: 0.9.6
Summary: A toolset to analyze videos of foraging animals.
Home-page: https://github.com/scholz-lab/PharaGlow
Author: M.Scholz
Author-email: "M.Scholz" <monika.k.scholz@gmail.com>
Maintainer: Omar Valerio
Maintainer-email: Omar Valerio <omar.valerio@mpinb.mpg.de>
License: GNU GENERAL PUBLIC LICENSE
Project-URL: PharaGlow Homepage, https://github.com/scholz-lab/PharaGlow
Project-URL: Bug Reports, https://github.com/scholz-lab/PharaGlow/issues
Project-URL: Source, https://github.com/scholz-lab/PharaGlow
Project-URL: API Reference, https://scholz-lab.github.io/PharaGlow/build/html/pharaglow.html
Keywords: toolset,tracking,feeding,behaviour,pumping
Classifier: Development Status :: 5 - Production/Stable
Classifier: Intended Audience :: Developers
Classifier: Topic :: Software Development :: Build Tools
Classifier: License :: OSI Approved :: GNU General Public License v3 (GPLv3)
Classifier: Programming Language :: Python :: 3
Classifier: Programming Language :: Python :: 3.8
Classifier: Programming Language :: Python :: 3.9
Classifier: Programming Language :: Python :: 3.10
Classifier: Programming Language :: Python :: 3.11
Classifier: Programming Language :: Python :: 3 :: Only
Requires-Python: >=3.8
License-File: LICENSE
Requires-Dist: numpy
Requires-Dist: scipy
Requires-Dist: pyampd
Requires-Dist: pandas
Requires-Dist: pillow >=10.0.1
Requires-Dist: pims
Requires-Dist: scikit-image
Requires-Dist: trackpy
Requires-Dist: papermill
Requires-Dist: matplotlib
Requires-Dist: ipykernel
Requires-Dist: imagecodecs
